silabeador/__init__.py
silabeador/exceptions.lst
silabeador/silabeador.py
silabeador-1.2.1.dist-info/LICENCE
silabeador-1.2.1.dist-info/METADATA
silabeador-1.2.1.dist-info/WHEEL
silabeador-1.2.1.dist-info/entry_points.txt
silabeador-1.2.1.dist-info/top_level.txt
silabeador-1.2.1.dist-info/RECORD
