Metadata-Version: 2.1
Name: silabeador
Version: 1.2.1
Summary: A Python library of methods and functions for syllabic division and prosodic stress detecting for Spanish
Home-page: https://github.com/fsanzl/silabeador
Author: Fernando Sanz-Lázaro
Author-email: fsanzl@gmail.com
License: LGPL
Project-URL: Source, https://github.com/fsanzl/silabeador/
Project-URL: Tracker, https://github.com/fsanzl/silabeador/issues
Classifier: License :: OSI Approved :: GNU Lesser General Public License v2 or later (LGPLv2+)
Classifier: Programming Language :: Python :: 3
Classifier: Programming Language :: Python :: 3.9
Classifier: Programming Language :: Python :: 3.8
Classifier: Programming Language :: Python :: 3.7
Classifier: Programming Language :: Python :: 3.6
Classifier: Programming Language :: Python :: 3.5
Classifier: Natural Language :: Spanish
Requires-Python: >=3.5
License-File: LICENCE
